physico/__init__.py
physico/dataset.py
physico/visualize.py
physico-0.1.0.dist-info/METADATA
physico-0.1.0.dist-info/WHEEL
physico-0.1.0.dist-info/top_level.txt
physico-0.1.0.dist-info/RECORD
