Metadata-Version: 2.1
Name: physico
Version: 0.1.0
Summary: Tools for PhysiCo Dataset
Home-page: https://github.com/physico-benchmark/physico
Author: Shunchi Zhang
Author-email: Shunchi Zhang <shunchizhang.cs@gmail.com>
Project-URL: Homepage, https://physico-benchmark.github.io
Project-URL: Repository, https://github.com/physico-benchmark/physico
Requires-Dist: datasets
Requires-Dist: matplotlib
Requires-Dist: numpy
Requires-Dist: requests
